setup.py
client/__init__.py
client/client.py
client/client/__init__.py
client/client/client_db.py
client/client/client_main_window.py
client/client/client_ui.py
client/client/interaction.py
client/client/qdialogs.py
client/common/__init__.py
client/common/decorators.py
client/common/default_conf.py
client/common/metaclasses.py
client/common/utils.py
client/logs/__init__.py
client/logs/log_configs/__init__.py
client/logs/log_configs/client_log_config.py
client/logs/log_configs/server_log_config.py
client/tests/__init__.py
client/tests/unittests/__init__.py
client/tests/unittests/test_client.py
client/tests/unittests/test_server.py
client/tests/unittests/test_utils.py
messenger_client_nagorny.egg-info/PKG-INFO
messenger_client_nagorny.egg-info/SOURCES.txt
messenger_client_nagorny.egg-info/dependency_links.txt
messenger_client_nagorny.egg-info/requires.txt
messenger_client_nagorny.egg-info/top_level.txt